o4/__init__.py
o4/broadcast/__init__.py
o4/broadcast/broadcast.py
o4/broadcast/faker.py
o4/classification/__init__.py
o4/classification/char_sequence.py
o4/classification/license_plate.py
o4/core/__init__.py
o4/core/algorithm.py
o4/core/dataset.py
o4/core/drawer.py
o4/core/point.py
o4/core/settings.py
o4/detection/__init__.py
o4/detection/detection.py
o4/detection/detectors/__init__.py
o4/detection/detectors/detector.py
o4/detection/detectors/license_plate/__init__.py
o4/detection/detectors/license_plate/detector.py
o4/detection/detectors/license_plate/t.py
o4/detection/detectors/license_plate/openalpr_64/__init__.py
o4/detection/detectors/license_plate/openalpr_64/python/__init__.py
o4/detection/detectors/license_plate/openalpr_64/python/setup.py
o4/detection/detectors/license_plate/openalpr_64/python/test.py
o4/detection/detectors/yolo3_keras/__init__.py
o4/detection/detectors/yolo3_keras/coco_annotation.py
o4/detection/detectors/yolo3_keras/convert.py
o4/detection/detectors/yolo3_keras/detector.py
o4/detection/detectors/yolo3_keras/kmeans.py
o4/detection/detectors/yolo3_keras/train.py
o4/detection/detectors/yolo3_keras/train_bottleneck.py
o4/detection/detectors/yolo3_keras/voc_annotation.py
o4/detection/detectors/yolo3_keras/yolo.py
o4/detection/detectors/yolo3_keras/yolo_video.py
o4/detection/detectors/yolo3_keras/yolo3/__init__.py
o4/detection/detectors/yolo3_keras/yolo3/model.py
o4/detection/detectors/yolo3_keras/yolo3/utils.py
o4/detection/detectors/yolo3_opencv/__init__.py
o4/detection/detectors/yolo3_opencv/config.py
o4/detection/detectors/yolo3_opencv/detector.py
o4/features/__init__.py
o4/features/feature.py
o4/features/counter/__init__.py
o4/features/counter/counter.py
o4/features/counter/unique_objects.py
o4/features/history/__init__.py
o4/features/history/history.py
o4/features/intersection/__init__.py
o4/features/intersection/area_counter.py
o4/features/intersection/line.py
o4/features/location/__init__.py
o4/features/location/detections_boxes.py
o4-0.5.2.dist-info/LICENSE
o4-0.5.2.dist-info/METADATA
o4-0.5.2.dist-info/WHEEL
o4-0.5.2.dist-info/top_level.txt
o4-0.5.2.dist-info/RECORD
